verify_response/__init__.py
verify_response/main.py
verify_response/prompts.py
verify_response-2025.12.21152239.dist-info/METADATA
verify_response-2025.12.21152239.dist-info/WHEEL
verify_response-2025.12.21152239.dist-info/top_level.txt
verify_response-2025.12.21152239.dist-info/RECORD
