Metadata-Version: 2.4
Name: verify-response
Version: 2025.12.21152239
Summary: A new package enables users to provide text inputs and receive reliably structured responses that clearly present key information with confidence indicators, reducing misunderstanding and overconfiden
Author-email: verify-response <hi@eugene.plus>
License: MIT
Project-URL: Homepage, https://github.com/chigwell/verify-response
Requires-Python: >=3.9
Requires-Dist: langchain-llm7>=0.0.0
Requires-Dist: llmatch-messages>=0.0.0
Requires-Dist: langchain-core>=0.3.0
